pyutils/__init__.py
pyutils/autoupgrade.py
pyutils/executor.py
pyutils/fsext.py
pyutils/shorthand.py
pyutils/simplelogger.py
pyutils/templite.py
tests/__init__.py
tests/test_autoupgrade.py
tests/test_executor.py
tests/test_fsext.py
pyutils_basstal-0.2.9.dist-info/LICENSE.txt
pyutils_basstal-0.2.9.dist-info/METADATA
pyutils_basstal-0.2.9.dist-info/WHEEL
pyutils_basstal-0.2.9.dist-info/top_level.txt
pyutils_basstal-0.2.9.dist-info/RECORD
