Metadata-Version: 2.1
Name: pyutils-basstal
Version: 0.2.9
Summary: self used py utils
Home-page: https://github.com/basstal/pyutils
Author: basstal
Author-email: 330475004@qq.com
Keywords: utils,development
Classifier: Development Status :: 3 - Alpha
Classifier: Intended Audience :: Developers
Classifier: Topic :: Software Development :: Libraries
Classifier: License :: OSI Approved :: MIT License
Classifier: Programming Language :: Python :: 3
Classifier: Programming Language :: Python :: 3.7
Classifier: Programming Language :: Python :: 3.8
Classifier: Programming Language :: Python :: 3.9
Classifier: Programming Language :: Python :: 3.10
Classifier: Programming Language :: Python :: 3 :: Only
Requires-Python: >=3.7, <4
License-File: LICENSE.txt
Requires-Dist: charade
Requires-Dist: semantic-version
Requires-Dist: beautifulsoup4
Requires-Dist: deprecated
